FaceSetBuilder/__init__.py
FaceSetBuilder/cluster_faces.py
FaceSetBuilder/constants.py
FaceSetBuilder/encode_faces.py
FaceSetBuilder/encodings.pickle
FaceSetBuilder/gui.py
FaceSetBuilder/haarcascade_frontalface_default.xml
FaceSetBuilder/main.py
FaceSetBuilder/myTkinter.py
FaceSetBuilder-2.dist-info/LICENSE.txt
FaceSetBuilder-2.dist-info/METADATA
FaceSetBuilder-2.dist-info/WHEEL
FaceSetBuilder-2.dist-info/entry_points.txt
FaceSetBuilder-2.dist-info/top_level.txt
FaceSetBuilder-2.dist-info/RECORD
