Metadata-Version: 2.1
Name: FaceSetBuilder
Version: 2
Summary: App to cluster faces from a dataset directory.
Home-page: https://github.com/max-dotpy/FaceSetBuilder
Author: Massimo Cosimo
Author-email: massimo.cosimo.95@gmail.com
License: MIT
Download-URL: https://github.com/max-dotpy/FaceSetBuilder/archive/v0.1.tar.gz
Keywords: tkinter,GUI,Face Recognition,Face Clustering,beginners-friendly,Dataset
Platform: UNKNOWN
Classifier: Development Status :: 4 - Beta
Classifier: Intended Audience :: Developers
Classifier: Topic :: Software Development :: Build Tools
Classifier: License :: OSI Approved :: MIT License
Classifier: Programming Language :: Python :: 3
Classifier: Programming Language :: Python :: 3.4
Classifier: Programming Language :: Python :: 3.5
Classifier: Programming Language :: Python :: 3.6
Classifier: Programming Language :: Python :: 3.7
Requires-Dist: Pillow
Requires-Dist: opencv-python
Requires-Dist: numpy
Requires-Dist: imutils
Requires-Dist: scikit-learn
